README.md
setup.py
budgetml/__init__.py
budgetml/basepredictor.py
budgetml/constants.py
budgetml/main.py
budgetml/template-compose.yaml
budgetml/template-nginx.conf
budgetml/template.Dockerfile
budgetml.egg-info/PKG-INFO
budgetml.egg-info/SOURCES.txt
budgetml.egg-info/dependency_links.txt
budgetml.egg-info/requires.txt
budgetml.egg-info/top_level.txt
budgetml/autostarter/__init__.py
budgetml/autostarter/main.py
budgetml/gcp/__init__.py
budgetml/gcp/addresses.py
budgetml/gcp/compute.py
budgetml/gcp/function.py
budgetml/gcp/pubsub.py
budgetml/gcp/scheduler.py
budgetml/gcp/storage.py
budgetml/gcp/utils.py