Metadata-Version: 2.1
Name: budgetml
Version: 0.1.2
Summary: BudgetML: Deploy ML models on a budget.
Home-page: https://github.com/ebhy/budgetml
Author: ebhy Inc.
Author-email: htahir111@gmail.com
License: Apache License 2.0
Keywords: deploy,machine learning,deep learning,inference,api,prediction,deep learning,data science
Platform: UNKNOWN
Classifier: Development Status :: 4 - Beta
Classifier: Intended Audience :: Developers
Classifier: Topic :: Software Development :: Libraries
Classifier: License :: OSI Approved :: Apache Software License
Classifier: Programming Language :: Python :: 3.6
Requires-Python: >=3.6, <3.9.0
